voicechatengine/__init__.py
voicechatengine/base_engine.py
voicechatengine/config.py
voicechatengine/voice_engine.py
voicechatengine/audioengine/__init__.py
voicechatengine/audioengine/audioengine/__init__.py
voicechatengine/audioengine/audioengine/audio_engine.py
voicechatengine/audioengine/audioengine/audio_interfaces.py
voicechatengine/audioengine/audioengine/audio_manager.py
voicechatengine/audioengine/audioengine/audio_processor.py
voicechatengine/audioengine/audioengine/audio_types.py
voicechatengine/audioengine/audioengine/buffered_audio_player.py
voicechatengine/audioengine/audioengine/direct_audio_capture.py
voicechatengine/audioengine/audioengine/exceptions.py
voicechatengine/audioengine/audioengine/fast_vad_detector.py
voicechatengine/audioengine/smoke_tests/__init__.py
voicechatengine/audioengine/smoke_tests/test10_audio_integration.py
voicechatengine/audioengine/smoke_tests/test11_realtime_voice_streaming.py
voicechatengine/audioengine/smoke_tests/test12_audio_benchmarks.py
voicechatengine/audioengine/smoke_tests/test13_base_engine_audio_engine_compatibility.py
voicechatengine/audioengine/smoke_tests/test1_audio_types.py
voicechatengine/audioengine/smoke_tests/test2_audio_processor.py
voicechatengine/audioengine/smoke_tests/test3_audio_engine.py
voicechatengine/audioengine/smoke_tests/test4_direct_audio_capture.py
voicechatengine/audioengine/smoke_tests/test5_direct_audio_player.py
voicechatengine/audioengine/smoke_tests/test6_vad_detector.py
voicechatengine/audioengine/smoke_tests/test7_audio_manager.py
voicechatengine/audioengine/smoke_tests/test8_buffered_player.py
voicechatengine/audioengine/smoke_tests/test9_audio_pipeline.py
voicechatengine/big_lane/__init__.py
voicechatengine/big_lane/audio_pipeline.py
voicechatengine/big_lane/event_bus.py
voicechatengine/big_lane/response_aggregator.py
voicechatengine/big_lane/stream_orchestrator.py
voicechatengine/connections/__init__.py
voicechatengine/connections/deprecated_client.py
voicechatengine-0.0.3.dist-info/METADATA
voicechatengine-0.0.3.dist-info/WHEEL
voicechatengine-0.0.3.dist-info/top_level.txt
voicechatengine-0.0.3.dist-info/RECORD
