Metadata-Version: 2.4
Name: voicechatengine
Version: 0.0.3
Summary: A production-ready Python framework for building real-time AI voice chat applications using OpenAI s Realtime API 
Author: enes kuzucu
Classifier: Development Status :: 3 - Alpha
Classifier: Intended Audience :: Developers
Classifier: License :: OSI Approved :: MIT License
Classifier: Programming Language :: Python :: 3
Classifier: Programming Language :: Python :: 3.7
Classifier: Programming Language :: Python :: 3.8
Classifier: Programming Language :: Python :: 3.9
Classifier: Programming Language :: Python :: 3.10
Classifier: Operating System :: OS Independent
Requires-Python: >=3.7
Requires-Dist: websockets>=11.0.0
Requires-Dist: python-dotenv>=1.0.0
Requires-Dist: aiohttp>=3.8.0
Requires-Dist: numpy>=1.21.0
Requires-Dist: pydub>=0.25.0
Requires-Dist: pynput
Requires-Dist: scipy>=1.9.0
Requires-Dist: matplotlib>=3.5.0
Requires-Dist: sounddevice
Requires-Dist: soundfile
Dynamic: author
Dynamic: classifier
Dynamic: description
Dynamic: description-content-type
Dynamic: requires-dist
Dynamic: requires-python
Dynamic: summary
